zodchy_outbox/__init__.py
zodchy_outbox/actors/__init__.py
zodchy_outbox/actors/processing.py
zodchy_outbox/actors/registration.py
zodchy_outbox/contracts/__init__.py
zodchy_outbox/contracts/enums.py
zodchy_outbox/contracts/identity.py
zodchy_outbox/contracts/messages.py
zodchy_outbox/contracts/storage.py
zodchy_outbox/contracts/types.py
zodchy_outbox/instance.py
zodchy_outbox/storages/__init__.py
zodchy_outbox/storages/rdbs/__init__.py
zodchy_outbox/storages/rdbs/config.py
zodchy_outbox/storages/rdbs/migrations/__init__.py
zodchy_outbox/storages/rdbs/migrations/v0.py
zodchy_outbox/storages/rdbs/migrator.py
zodchy_outbox/storages/rdbs/readers/__init__.py
zodchy_outbox/storages/rdbs/readers/generic.py
zodchy_outbox/storages/rdbs/readers/tasks.py
zodchy_outbox/storages/rdbs/schema.py
zodchy_outbox/storages/rdbs/writers/__init__.py
zodchy_outbox/storages/rdbs/writers/generic.py
zodchy_outbox/storages/rdbs/writers/messages.py
zodchy_outbox/storages/rdbs/writers/tasks.py
zodchy_outbox-0.2.4.dist-info/METADATA
zodchy_outbox-0.2.4.dist-info/WHEEL
zodchy_outbox-0.2.4.dist-info/RECORD
